dials_dependencies/__init__.py
dials_dependencies/test_dependencies.py
dials_dependencies-0.9.0.dist-info/LICENSE
dials_dependencies-0.9.0.dist-info/METADATA
dials_dependencies-0.9.0.dist-info/WHEEL
dials_dependencies-0.9.0.dist-info/top_level.txt
dials_dependencies-0.9.0.dist-info/RECORD
