Metadata-Version: 2.1
Name: dials-dependencies
Version: 0.9.0
Summary: DIALS Dependencies
Home-page: https://github.com/dials/dials-dependencies
Author: DIALS
Author-email: dials-support@lists.sourceforge.net
License: BSD license
Platform: UNKNOWN
Classifier: Development Status :: 3 - Alpha
Classifier: Intended Audience :: Developers
Classifier: License :: OSI Approved :: BSD License
Classifier: Natural Language :: English
Classifier: Programming Language :: Python :: 2
Classifier: Programming Language :: Python :: 2.7
Classifier: Programming Language :: Python :: 3
Classifier: Programming Language :: Python :: 3.5
Classifier: Programming Language :: Python :: 3.6
Classifier: Programming Language :: Python :: 3.7
Classifier: Programming Language :: Python :: 3.8
Requires-Dist: dials-data (>=2.0.38)
Requires-Dist: Jinja2
Requires-Dist: h5py
Requires-Dist: mock (>=3.0.5)
Requires-Dist: msgpack
Requires-Dist: orderedset
Requires-Dist: procrunner (>=1.0.2)
Requires-Dist: psutil
Requires-Dist: pytest (<5.0,>=4.5)
Requires-Dist: pytest-mock
Requires-Dist: pytest-xdist (>=1.28.0)
Requires-Dist: scikit-learn[alldeps] (<0.21)
Requires-Dist: scipy
Requires-Dist: six
Requires-Dist: tabulate
Requires-Dist: tqdm (==4.23.4)
